{
    "01:00:embedded message": {
        "01:00:Varint": 245, 
        "02:01:Varint": 100925, 
        "03:02:string": "PAGEACTIVITY_1", 
        "04:03:Varint": 1, 
        "05:04:Varint": 2016, 
        "05:05:Varint": 7, 
        "05:06:Varint": 25, 
        "05:07:Varint": 12, 
        "05:08:Varint": 0, 
        "05:09:Varint": 0, 
        "06:10:Varint": 2099, 
        "06:11:Varint": 7, 
        "06:12:Varint": 26, 
        "06:13:Varint": 12, 
        "06:14:Varint": 0, 
        "06:15:Varint": 0, 
        "07:16:Varint": 100928, 
        "08:17:Varint": 0, 
        "09:18:string": "https://nq.games.laohu.com/mjj/iosny/index.html", 
        "10:19:string": "https://nq.games.laohu.com/mjj/adrny/index.html", 
        "11:20:Varint": 33
    }, 
    "01:01:embedded message": {
        "01:00:Varint": 245, 
        "02:01:Varint": 100926, 
        "03:02:string": "PAGEACTIVITY_2", 
        "04:03:Varint": 2, 
        "05:04:Varint": 2016, 
        "05:05:Varint": 7, 
        "05:06:Varint": 25, 
        "05:07:Varint": 12, 
        "05:08:Varint": 0, 
        "05:09:Varint": 0, 
        "06:10:Varint": 2016, 
        "06:11:Varint": 7, 
        "06:12:Varint": 26, 
        "06:13:Varint": 12, 
        "06:14:Varint": 0, 
        "06:15:Varint": 0, 
        "07:16:Varint": 100929, 
        "08:17:Varint": 0, 
        "09:18:string": "https://nq.games.laohu.com/lhj/cjydl0928/index.html", 
        "10:19:string": "https://nq.games.laohu.com/lhj/cjydl0928/index.html", 
        "11:20:Varint": 1
    }, 
    "01:02:embedded message": {
        "01:00:Varint": 245, 
        "02:01:Varint": 100927, 
        "03:02:string": "PAGEACTIVITY_3", 
        "04:03:Varint": 3, 
        "05:04:Varint": 2018, 
        "05:05:Varint": 3, 
        "05:06:Varint": 16, 
        "05:07:Varint": 7, 
        "05:08:Varint": 30, 
        "05:09:Varint": 0, 
        "06:10:Varint": 2020, 
        "06:11:Varint": 8, 
        "06:12:Varint": 3, 
        "06:13:Varint": 18, 
        "06:14:Varint": 59, 
        "06:15:Varint": 0, 
        "07:16:Varint": 110725, 
        "08:17:Varint": 109543, 
        "09:18:string": "http://m.laohu.com/paihang/index.html?", 
        "10:19:string": "http://m.laohu.com/paihang/index.html?", 
        "11:20:Varint": 2
    }, 
    "01:03:embedded message": {
        "01:00:Varint": 245, 
        "02:01:Varint": 100932, 
        "03:02:string": "PAGEACTIVITY_4", 
        "04:03:Varint": 3, 
        "05:04:Varint": 2016, 
        "05:05:Varint": 7, 
        "05:06:Varint": 25, 
        "05:07:Varint": 12, 
        "05:08:Varint": 0, 
        "05:09:Varint": 0, 
        "06:10:Varint": 2020, 
        "06:11:Varint": 8, 
        "06:12:Varint": 3, 
        "06:13:Varint": 15, 
        "06:14:Varint": 59, 
        "06:15:Varint": 0, 
        "07:16:Varint": 112738, 
        "08:17:Varint": 112737, 
        "09:18:string": "http://m.laohu.com/97443696020180717oneh5/index.html?", 
        "10:19:string": "http://m.laohu.com/97443696020180717oneh5/index.html?", 
        "11:20:Varint": 2
    }, 
    "01:04:embedded message": {
        "01:00:Varint": 245, 
        "02:01:Varint": 100933, 
        "03:02:string": "PAGEACTIVITY_5", 
        "04:03:Varint": 3, 
        "05:04:Varint": 2016, 
        "05:05:Varint": 7, 
        "05:06:Varint": 25, 
        "05:07:Varint": 12, 
        "05:08:Varint": 0, 
        "05:09:Varint": 0, 
        "06:10:Varint": 2016, 
        "06:11:Varint": 7, 
        "06:12:Varint": 26, 
        "06:13:Varint": 12, 
        "06:14:Varint": 0, 
        "06:15:Varint": 0, 
        "07:16:Varint": 100930, 
        "08:17:Varint": 100934, 
        "09:18:string": "http://10.2.48.172/hjxm/index.html?", 
        "10:19:string": "http://10.2.48.172/hjxm/index.html?", 
        "11:20:Varint": 1
    }, 
    "01:05:embedded message": {
        "01:00:Varint": 245, 
        "02:01:Varint": 132131, 
        "03:02:string": "PAGEACTIVITY_6", 
        "04:03:Varint": 3, 
        "05:04:Varint": 2016, 
        "05:05:Varint": 7, 
        "05:06:Varint": 25, 
        "05:07:Varint": 12, 
        "05:08:Varint": 0, 
        "05:09:Varint": 0, 
        "06:10:Varint": 2099, 
        "06:11:Varint": 7, 
        "06:12:Varint": 26, 
        "06:13:Varint": 12, 
        "06:14:Varint": 0, 
        "06:15:Varint": 0, 
        "07:16:Varint": 134252, 
        "08:17:Varint": 132132, 
        "09:18:string": "http://nq.games.laohu.com/m/chinaunicom/indexchinaldy.html?", 
        "10:19:string": "http://nq.games.laohu.com/m/chinaunicom/indexchinaldy.html?", 
        "11:20:Varint": 3
    }
}