{
    "01:00:embedded message": {
        "01:00:Varint": 235, 
        "02:01:Varint": 89280, 
        "03:02:string": "iphone_x", 
        "04:03:Varint": 2436, 
        "05:04:Varint": 1125, 
        "06:05:Varint": 132
    }, 
    "01:01:embedded message": {
        "01:00:Varint": 235, 
        "02:01:Varint": 89281, 
        "03:02:string": "oppo_bang", 
        "04:03:Varint": 2280, 
        "05:04:Varint": 1080, 
        "06:05:Varint": 132
    }, 
    "01:02:embedded message": {
        "01:00:Varint": 235, 
        "02:01:Varint": 89344, 
        "03:02:string": "huawei_p20", 
        "04:03:Varint": 2244, 
        "05:04:Varint": 1080, 
        "06:05:Varint": 132
    }, 
    "01:03:embedded message": {
        "01:00:Varint": 235, 
        "02:01:Varint": 89346, 
        "03:02:string": "huawei_p20_pro", 
        "04:03:Varint": 2240, 
        "05:04:Varint": 1080, 
        "06:05:Varint": 132
    }, 
    "01:04:embedded message": {
        "01:00:Varint": 235, 
        "02:01:Varint": 111477, 
        "03:02:embedded message": {
            "12:01:64-bit": 8.87838318935456e+247, 
            "13:02:Varint": 97, 
            "15:00:Varint": 105
        }, 
        "04:03:Varint": 2160, 
        "05:04:Varint": 1080, 
        "06:05:Varint": 132
    }, 
    "01:05:embedded message": {
        "01:00:Varint": 235, 
        "02:01:Varint": 111478, 
        "03:02:string": "sanxing_galaxy", 
        "04:03:Varint": 2960, 
        "05:04:Varint": 1440, 
        "06:05:Varint": 132
    }, 
    "01:06:embedded message": {
        "01:00:Varint": 235, 
        "02:01:Varint": 111479, 
        "03:02:string": "xiaomi_hongmi", 
        "04:03:Varint": 1440, 
        "05:04:Varint": 720, 
        "06:05:Varint": 132
    }, 
    "01:07:embedded message": {
        "01:00:Varint": 235, 
        "02:01:Varint": 118979, 
        "03:02:string": "fit_1", 
        "04:03:Varint": 2316, 
        "05:04:Varint": 1080, 
        "06:05:Varint": 132
    }, 
    "01:08:embedded message": {
        "01:00:Varint": 235, 
        "02:01:Varint": 118980, 
        "03:02:string": "fit_2", 
        "04:03:Varint": 2340, 
        "05:04:Varint": 1080, 
        "06:05:Varint": 132
    }, 
    "01:09:embedded message": {
        "01:00:Varint": 235, 
        "02:01:Varint": 118981, 
        "03:02:string": "fit_3", 
        "04:03:Varint": 2280, 
        "05:04:Varint": 1080, 
        "06:05:Varint": 132
    }, 
    "01:10:embedded message": {
        "01:00:Varint": 235, 
        "02:01:Varint": 118982, 
        "03:02:string": "fit_4", 
        "04:03:Varint": 2240, 
        "05:04:Varint": 1080, 
        "06:05:Varint": 132
    }, 
    "01:11:embedded message": {
        "01:00:Varint": 235, 
        "02:01:Varint": 118983, 
        "03:02:string": "fit_5", 
        "04:03:Varint": 2246, 
        "05:04:Varint": 1080, 
        "06:05:Varint": 132
    }, 
    "01:12:embedded message": {
        "01:00:Varint": 235, 
        "02:01:Varint": 118984, 
        "03:02:string": "fit_6", 
        "04:03:Varint": 2160, 
        "05:04:Varint": 1080, 
        "06:05:Varint": 132
    }, 
    "01:13:embedded message": {
        "01:00:Varint": 235, 
        "02:01:Varint": 118985, 
        "03:02:string": "fit_7", 
        "04:03:Varint": 1440, 
        "05:04:Varint": 720, 
        "06:05:Varint": 132
    }, 
    "01:14:embedded message": {
        "01:00:Varint": 235, 
        "02:01:Varint": 118986, 
        "03:02:string": "fit_8", 
        "04:03:Varint": 1520, 
        "05:04:Varint": 720, 
        "06:05:Varint": 132
    }, 
    "01:15:embedded message": {
        "01:00:Varint": 235, 
        "02:01:Varint": 118987, 
        "03:02:string": "fit_9", 
        "04:03:Varint": 2960, 
        "05:04:Varint": 1440, 
        "06:05:Varint": 132
    }, 
    "01:16:embedded message": {
        "01:00:Varint": 235, 
        "02:01:Varint": 118988, 
        "03:02:string": "fit_10", 
        "04:03:Varint": 2436, 
        "05:04:Varint": 1125, 
        "06:05:Varint": 132
    }, 
    "01:17:embedded message": {
        "01:00:Varint": 235, 
        "02:01:Varint": 118989, 
        "03:02:string": "fit_11", 
        "04:03:Varint": 1792, 
        "05:04:Varint": 828, 
        "06:05:Varint": 132
    }, 
    "01:18:embedded message": {
        "01:00:Varint": 235, 
        "02:01:Varint": 118990, 
        "03:02:string": "fit_12", 
        "04:03:Varint": 2688, 
        "05:04:Varint": 1242, 
        "06:05:Varint": 132
    }
}