{
    "01:00:embedded message": {
        "01:00:Varint": 264, 
        "02:01:Varint": 135039, 
        "03:02:string": "bgm_test_18", 
        "04:03:Varint": 139438, 
        "05:04:Varint": 135073, 
        "06:05:Varint": 132802, 
        "07:06:Varint": 1, 
        "08:07:Varint": 18567, 
        "09:08:Varint": 22011, 
        "10:09:Varint": 135055, 
        "11:10:Varint": 40
    }, 
    "01:01:embedded message": {
        "01:00:Varint": 264, 
        "02:01:Varint": 132053, 
        "03:02:string": "bgm_test_5", 
        "04:03:Varint": 135063, 
        "05:04:Varint": 135073, 
        "06:05:Varint": 132801, 
        "07:06:Varint": 2, 
        "08:07:Varint": 961, 
        "09:08:Varint": 22011, 
        "10:09:Varint": 132058, 
        "11:10:Varint": 40
    }, 
    "01:02:embedded message": {
        "01:00:Varint": 264, 
        "02:01:Varint": 132048, 
        "03:02:string": "bgm_test_6", 
        "04:03:Varint": 135064, 
        "05:04:Varint": 135073, 
        "06:05:Varint": 132801, 
        "07:06:Varint": 3, 
        "08:07:Varint": 18559, 
        "09:08:Varint": 22011, 
        "10:09:Varint": 132059, 
        "11:10:Varint": 40
    }, 
    "01:03:embedded message": {
        "01:00:Varint": 264, 
        "02:01:Varint": 132052, 
        "03:02:string": "bgm_test_4", 
        "04:03:Varint": 74875, 
        "05:04:Varint": 135073, 
        "06:05:Varint": 132802, 
        "07:06:Varint": 4, 
        "08:07:Varint": 24114, 
        "09:08:Varint": 22011, 
        "10:09:Varint": 132057, 
        "11:10:Varint": 40
    }, 
    "01:04:embedded message": {
        "01:00:Varint": 264, 
        "02:01:Varint": 135028, 
        "03:02:string": "bgm_test_7", 
        "04:03:Varint": 135065, 
        "05:04:Varint": 135073, 
        "06:05:Varint": 132801, 
        "07:06:Varint": 5, 
        "08:07:Varint": 962, 
        "09:08:Varint": 22011, 
        "10:09:Varint": 135044, 
        "11:10:Varint": 40
    }, 
    "01:05:embedded message": {
        "01:00:Varint": 264, 
        "02:01:Varint": 135029, 
        "03:02:string": "bgm_test_8", 
        "04:03:Varint": 135066, 
        "05:04:Varint": 135073, 
        "06:05:Varint": 132801, 
        "07:06:Varint": 6, 
        "08:07:Varint": 18560, 
        "09:08:Varint": 22011, 
        "10:09:Varint": 135045, 
        "11:10:Varint": 40
    }, 
    "01:06:embedded message": {
        "01:00:Varint": 264, 
        "02:01:Varint": 135030, 
        "03:02:string": "bgm_test_9", 
        "04:03:Varint": 135067, 
        "05:04:Varint": 135073, 
        "06:05:Varint": 132802, 
        "07:06:Varint": 7, 
        "08:07:Varint": 5289, 
        "09:08:Varint": 22011, 
        "10:09:Varint": 135046, 
        "11:10:Varint": 40
    }, 
    "01:07:embedded message": {
        "01:00:Varint": 264, 
        "02:01:Varint": 135031, 
        "03:02:string": "bgm_test_10", 
        "04:03:Varint": 135068, 
        "05:04:Varint": 135073, 
        "06:05:Varint": 132802, 
        "07:06:Varint": 8, 
        "08:07:Varint": 18561, 
        "09:08:Varint": 22011, 
        "10:09:Varint": 135047, 
        "11:10:Varint": 40
    }, 
    "01:08:embedded message": {
        "01:00:Varint": 264, 
        "02:01:Varint": 135032, 
        "03:02:string": "bgm_test_11", 
        "04:03:Varint": 33667, 
        "05:04:Varint": 135073, 
        "06:05:Varint": 132802, 
        "07:06:Varint": 9, 
        "08:07:Varint": 963, 
        "09:08:Varint": 22011, 
        "10:09:Varint": 135048, 
        "11:10:Varint": 40
    }, 
    "01:09:embedded message": {
        "01:00:Varint": 264, 
        "02:01:Varint": 135033, 
        "03:02:string": "bgm_test_12", 
        "04:03:Varint": 135069, 
        "05:04:Varint": 135073, 
        "06:05:Varint": 132802, 
        "07:06:Varint": 10, 
        "08:07:Varint": 18566, 
        "09:08:Varint": 22011, 
        "10:09:Varint": 135049, 
        "11:10:Varint": 40
    }
}